Metadata-Version: 2.1
Name: astbil-calculator
Version: 0.1
Summary: Calculator performing basic mathematical operations
Home-page: UNKNOWN
Author: Asta Bilaišytė
License: UNKNOWN
Platform: UNKNOWN
